./.gitignore
./.python-version
./LICENSE
./PKG-INFO
./PUBLISH.md
./README.md
./main.py
./pyproject.toml
./tree.py
./uv.lock
zhtree-0.1.0.dist-info/METADATA
zhtree-0.1.0.dist-info/WHEEL
zhtree-0.1.0.dist-info/entry_points.txt
zhtree-0.1.0.dist-info/licenses/LICENSE
zhtree-0.1.0.dist-info/RECORD
