Metadata-Version: 2.4
Name: zhtree
Version: 0.1.0
Summary: 增强版 tree 命令 - 跨平台目录树显示工具，类似 Linux 的 tree 命令
Project-URL: Homepage, https://github.com/yourusername/zhtree
Project-URL: Repository, https://github.com/yourusername/zhtree
Project-URL: Issues, https://github.com/yourusername/zhtree/issues
Author-email: Your Name <your.email@example.com>
License: MIT
License-File: LICENSE
Keywords: cli,command-line,directory,filesystem,tree
Classifier: Development Status :: 4 - Beta
Classifier: Intended Audience :: Developers
Classifier: License :: OSI Approved :: MIT License
Classifier: Programming Language :: Python :: 3
Classifier: Programming Language :: Python :: 3.8
Classifier: Programming Language :: Python :: 3.9
Classifier: Programming Language :: Python :: 3.10
Classifier: Programming Language :: Python :: 3.11
Classifier: Programming Language :: Python :: 3.12
Classifier: Topic :: Utilities
Requires-Python: >=3.8
